setup.py
iplock/__init__.py
iplock/lock.py
iplock/tools.py
iplock.egg-info/PKG-INFO
iplock.egg-info/SOURCES.txt
iplock.egg-info/dependency_links.txt
iplock.egg-info/top_level.txt