Metadata-Version: 1.0
Name: iplock
Version: 0.9
Summary: duoshoubang copyright
Home-page: UNKNOWN
Author: tuxpy
Author-email: UNKNOWN
License: UNKNOWN
Platform: UNKNOWN
